recho/__init__.py
recho/cli.py
recho/recho.py
recho/reddit.py
recho-1.0.2.dist-info/DESCRIPTION.rst
recho-1.0.2.dist-info/METADATA
recho-1.0.2.dist-info/RECORD
recho-1.0.2.dist-info/WHEEL
recho-1.0.2.dist-info/entry_points.txt
recho-1.0.2.dist-info/metadata.json
recho-1.0.2.dist-info/top_level.txt
tests/__init__.py
tests/test_cli.py
tests/test_recho.py
