Metadata-Version: 2.0
Name: recho
Version: 1.0.2
Summary: repost Reddit activity from a user to Slack in near-realtime
Home-page: https://github.com/levi-rs/recho
Author: Levi Noecker
Author-email: levi.noecker@gmail.com
License: UNKNOWN
Keywords: reddit slack bot slackbot recho chat chatbot
Platform: UNKNOWN
Classifier: Development Status :: 5 - Production/Stable
Classifier: Intended Audience :: Developers
Classifier: Natural Language :: English
Classifier: License :: OSI Approved :: MIT License
Classifier: Operating System :: OS Independent
Classifier: Topic :: Communications :: Chat
Classifier: Programming Language :: Python :: 2
Classifier: Programming Language :: Python :: 2.7
Classifier: Programming Language :: Python :: 3
Classifier: Programming Language :: Python :: 3.5
Classifier: Programming Language :: Python :: 3.6
Classifier: Programming Language :: Python :: Implementation :: CPython
Requires-Dist: configparser (==3.5.0)
Requires-Dist: praw (>=5.3.0)
Requires-Dist: raven
Requires-Dist: slacker (==0.9.30)
